{
"type": "FeatureCollection",
"name": "Отменяемые остановки",
"crs": { "type": "name", "properties": { "name": "urn:ogc:def:crs:OGC:1.3:CRS84" } },
"features": [
{ "type": "Feature", "properties": { "fid": 1, "type": " отменяемая", "name": "Магазин Милана" }, "geometry": { "type": "Point", "coordinates": [ 39.956286831012186, 43.414970326988062 ] } },
{ "type": "Feature", "properties": { "fid": 2, "type": " отменяемая", "name": "Магазин Милана" }, "geometry": { "type": "Point", "coordinates": [ 39.956178420121482, 43.414580954977076 ] } },
{ "type": "Feature", "properties": { "fid": 3, "type": " отменяемая", "name": "Перелетная улица" }, "geometry": { "type": "Point", "coordinates": [ 39.96370943953076, 43.414428019585671 ] } }
]
}
